pyhdf5_handler/__init__.py
pyhdf5_handler/src/__init__.py
pyhdf5_handler/src/hdf5_handler.py
pyhdf5_handler/src/object_handler.py
pyhdf5_handler/tutorial/__init__.py
pyhdf5_handler/tutorial/complementary_test.py
pyhdf5_handler/tutorial/hdf5_io_tests.py
pyhdf5_handler-0.5.dist-info/METADATA
pyhdf5_handler-0.5.dist-info/WHEEL
pyhdf5_handler-0.5.dist-info/licenses/LICENSE
pyhdf5_handler-0.5.dist-info/RECORD
