Metadata-Version: 2.4
Name: pyhdf5_handler
Version: 0.5
Summary: A Python library to read and write data to HDF5 format. This library is based on the h5py (https://docs.h5py.org/en/stable/index.html) and has been developed by Maxime Jay-Allemand at Hydris hydrologie (https://www.hydris-hydrologie.fr/)
Project-URL: Homepage, https://codeberg.org/maximejay/pyhdf5_handler
Project-URL: Issues, https://codeberg.org/maximejay/pyhdf5_handler/issues
Author-email: Maxime Jay-Allemand <maxime.jay.allemand@hydris-hydrologie.fr>
License-File: LICENSE
Keywords: h5,h5py,hdf5
Classifier: Operating System :: OS Independent
Classifier: Programming Language :: Python :: 3
Requires-Python: >=3.9
Requires-Dist: h5py
Requires-Dist: numpy
Requires-Dist: pandas
